Xinsheng/README.md
Xinsheng/__init__.py
Xinsheng/__main__.py
Xinsheng/file.epub
Xinsheng/index.html
Xinsheng/css/__init__.py
Xinsheng/css/annotations.css
Xinsheng/css/main.css
Xinsheng/css/normalize.css
Xinsheng/css/popup.css
Xinsheng/font/__init__.py
Xinsheng/font/fontello.eot
Xinsheng/font/fontello.svg
Xinsheng/font/fontello.ttf
Xinsheng/font/fontello.woff
Xinsheng/img/__init__.py
Xinsheng/img/annotator-glyph-sprite.png
Xinsheng/img/annotator-icon-sprite.png
Xinsheng/img/apple-touch-icon.png
Xinsheng/img/cancelfullscreen.png
Xinsheng/img/close.png
Xinsheng/img/fullscreen.png
Xinsheng/img/loader.gif
Xinsheng/img/menu-icon.png
Xinsheng/img/save.png
Xinsheng/img/saved.png
Xinsheng/img/settings-s.png
Xinsheng/img/settings.png
Xinsheng/img/star.png
Xinsheng/js/__init__.py
Xinsheng/js/epub.js
Xinsheng/js/epub.min.js
Xinsheng/js/epub.min.map
Xinsheng/js/hooks.min.js
Xinsheng/js/hooks.min.map
Xinsheng/js/reader.js
Xinsheng/js/reader.js.map
Xinsheng/js/reader.min.js
Xinsheng/js/reader.min.map
Xinsheng/js/hooks/__init__.py
Xinsheng/js/hooks/extensions/__init__.py
Xinsheng/js/hooks/extensions/highlight.js
Xinsheng/js/libs/__init__.py
Xinsheng/js/libs/jquery.min.js
Xinsheng/js/libs/localforage.min.js
Xinsheng/js/libs/screenfull.js
Xinsheng/js/libs/screenfull.min.js
Xinsheng/js/libs/zip.min.js
Xinsheng/js/plugins/__init__.py
Xinsheng/js/plugins/hypothesis.js
Xinsheng/js/plugins/search.js
xinsheng-2024.3.5.0.dist-info/METADATA
xinsheng-2024.3.5.0.dist-info/WHEEL
xinsheng-2024.3.5.0.dist-info/entry_points.txt
xinsheng-2024.3.5.0.dist-info/top_level.txt
xinsheng-2024.3.5.0.dist-info/RECORD
